[
    {
        "nav_name": "Research and Records",
        "name": "Research and Records",
        "section_name": "Learn about Cheshire research and records.",
        "summary": "",
        "choices": [
            {
                "name": "Get started with research for your Cheshire ancestors.",
                "content": {
                    "hidden": [],
                    "images": [
                        "https://www.thefhguide.com/img/x-en-chs-over.jpg"
                    ],
                    "text": "<ol><a href=\"https://pixabay.com/en/little-moreton-hall-cheshire-old-1535313/\" target=\"_blank\"> <img src=\"../img/x-en-chs-over.jpg\" alt=\"\" width=\"450px\" border=\"1\" style=\"float:right; margin-left: 16px; border:1px solid #000; padding:0px;\"></a><li>Learn about finding your ancestors in Cheshire. <br><br><span class=\"star notranslate\">☆</span><a href=\"https://familysearch.org/wiki/en/Cheshire,_England_Genealogy\" target=\"_blank\"> <img src=\"../img/doc.png\" width=\"20\"> <span class=\"re\">FS Wiki: Cheshire England Genealogy</span></a></li><br><li>Get an overview of Cheshire research. <br><br><span class=\"star notranslate\">☆</span><a href=\"https://www.familyhistory.co.uk/county-records/cheshire-family-history/\" target=\"_blank\"> <img src=\"../img/doc.png\" width=\"20\"> <span class=\"re\">Cheshire Family History</span></a></li><br><li>Read this Quick Guide to Family History from the Cheshire Archives and Local Studies group. <br><br><span class=\"star notranslate\">☆</span><a href=\"https://www.cheshirearchives.org.uk/pdf/quick%20guide%20to%20family%20history%20-%20Final.pdf\" target=\"_blank\"> <img src=\"../img/doc.png\" width=\"20\"> <span class=\"re\">Quick Guide to Family History</span></a></li><br><li>Explore the <span class=\"star notranslate\">☆</span><a class=\"lk\" href=\"http://www.dustydocs.com/county/5/cheshire.html?country_id=1\" target=\"_blank\"><img src=\"../img/d.png\" width=\"2\">Dusty Docs site</a> for Cheshire research.</li><li>Explore a variety of records on the <span class=\"star notranslate\">☆</span><a class=\"lk\" href=\"https://www.ukbmd.org.uk/index.php?county=105&amp;form_action=county\" target=\"_blank\"><img src=\"../img/d.png\" width=\"2\">UK BMD site</a>.</li><li>Explore lists of <span class=\"star notranslate\">☆</span><a class=\"lk\" href=\"https://www.genuki.org.uk/big/eng/CHS#Towns\" target=\"_blank\"><img src=\"../img/d.png\" width=\"2\">towns and parishes</a> on the GenUKI site.</li><li>Explore Cheshire resources on the <span class=\"star notranslate\">☆</span><a class=\"lk\" href=\"https://www.familyhistorydirectory.co.uk/england/cheshire/\" target=\"_blank\"><img src=\"../img/d.png\" width=\"2\">Family History Directory site</a>.</li><li>Find additional resources for Cheshire research on the <a class=\"lk\" href=\"http://www.sheffieldindexers.com/Links/Links_Cheshire.html\" target=\"_blank\">Sheffield Indexers site</a>.</li></ol>",
                    "resources": []
                }
            },
            {
                "name": "Learn about the history of Cheshire.",
                "content": {
                    "hidden": [
                        {
                            "type": "exercises",
                            "content": "<ul style=\"list-style: none; margin-left: -20px;\"><li>* Good: Using the articles and videos in this Choice, write down key learnings for research resources. Then use the learnings for searches for an ancestor.</li><li>* Proficient: Same as above, for two or more ancestors. </li></ul><hr style=\"margin-left: 20px;\">"
                        }
                    ],
                    "images": [],
                    "text": "<ol><li>Learn about Cheshire history on Wikipedia. <br><br><span class=\"star notranslate\">☆</span><a href=\"https://en.wikipedia.org/wiki/History_of_Cheshire/\" target=\"_blank\"> <img src=\"../img/doc.png\" width=\"20\"> <span class=\"re\">History of Cheshire</span></a></li><br><li>Go into more depth with Cheshire history on the British History Online site.<br><br><span class=\"star notranslate\">☆</span><a href=\"https://www.british-history.ac.uk/vch/ches\" target=\"_blank\"> <img src=\"../img/doc.png\" width=\"20\"> <span class=\"re\">Victoria County History series</span></a></li><br><li>Explore this <a class=\"lk\" href=\"http://www.cheshirepedia.org/cheshire-timeline-cheshire-history/\" target=\"_blank\">timeline of Cheshire historical events</a>.</li></ol>",
                    "resources": []
                }
            }
        ]
    },
    {
        "nav_name": "Archives and Libraries",
        "name": "Archives and Libraries",
        "section_name": "Learn about Cheshire archives and libraries.",
        "summary": "",
        "choices": [
            {
                "name": "Learn about Cheshire archives and libraries.",
                "content": {
                    "hidden": [
                        {
                            "type": "exercises",
                            "content": "<ul style=\"list-style: none; margin-left: -20px;\"><li>* Good: Using the articles and videos in this Choice, write down key learnings for archives and libraries. Then use the learnings for searches for an ancestor.</li><li>* Proficient: Same as above, for two or more ancestors. </li></ul><hr style=\"margin-left: 20px;\">"
                        }
                    ],
                    "images": [
                        "https://www.thefhguide.com/img/x-en-chs-lib.JPG"
                    ],
                    "text": "<ol><a class=\"lk\" href=\"https://en.wikipedia.org/wiki/File:Humanities_Building_Cheshire_Academy.JPG\" target=\"_blank\"> <img src=\"../img/x-en-chs-lib.JPG\" alt=\"\" width=\"450px\" border=\"1\" style=\"float:right; margin-left: 16px; border:1px solid #000; padding:0px;\"></a><li>Learn about Cheshire archives and libraries in this FamilySearch Wiki article. <br><br><span class=\"star notranslate\">☆</span><a href=\"https://familysearch.org/wiki/en/Cheshire_Archives_and_Libraries\" target=\"_blank\"> <img src=\"../img/doc.png\" width=\"20\"> <span class=\"re\">FS—Wiki: Cheshire Archives and Libraries</span></a></li><br><li>Learn about researching your ancestors at the Cheshire Archives. <br><br><span class=\"star notranslate\">☆</span><a href=\"https://www.family-tree.co.uk/how-to-guides/how-to-find-your-cheshire-ancestors-at-cheshire-archives/\" target=\"_blank\"> <img src=\"../img/doc.png\" width=\"20\"> <span class=\"re\">How to find your Cheshire ancestors at Cheshire Archives</span></a></li><br><li>Explore the <span class=\"star notranslate\">☆</span><a class=\"lk\" href=\"http://www.genuki.org.uk/big/eng/CHS/index.html#Archives%20and%20Libraries\" target=\"_blank\"><img src=\"../img/d.png\" width=\"2\">archives and libraries link</a> on the GenUKI Cheshire site.</li><li>Search for <span class=\"star notranslate\">☆</span><a class=\"lk\" href=\"https://books.familysearch.org/primo_library/libweb/action/search.do?fn=search&amp;ct=search&amp;mode=Basic&amp;tab=default_tab&amp;indx=1&amp;dum=true&amp;srt=rank&amp;vid=FHD_PUBLIC&amp;frbg=&amp;vl%28freeText0%29=cheshire+england\" target=\"_blank\"><img src=\"../img/d.png\" width=\"2\">free online books on Cheshire research</a> on the FamilySearch site.</li></ol>",
                    "resources": []
                }
            }
        ]
    },
    {
        "nav_name": "Vital and Census Records",
        "name": "Vital and Census Records",
        "section_name": "Learn about Cheshire civil registration, BMD, and census records.",
        "summary": "",
        "choices": [
            {
                "name": "Explore Cheshire civil registration and vital records.",
                "content": {
                    "hidden": [],
                    "images": [
                        "https://www.thefhguide.com/img/eng/che-nantwich.jpg"
                    ],
                    "text": "<ol><a href=\"https://en.wikipedia.org/wiki/Cheshire#/media/File:46_&amp;_48_High_Street,_Nantwich.JPG\" target=\"_blank\"><img src=\"../img/eng/che-nantwich.jpg\" alt=\"\" width=\"100%\" style=\"float:right; margin-left: 16px; margin-top: 8px; margin-bottom: 16px; max-width: 400px; border:1px solid #000; padding:0px;\"></a><li>Learn about Cheshire civil registration in this article. <br><br><span class=\"star notranslate\">☆</span><a href=\"https://www.cheshirearchives.org.uk/family-history/births-marriages-and-deaths.aspx\" target=\"_blank\"> <img src=\"../img/doc.png\" width=\"20\"> <span class=\"re\">Births, Marriages, and Deaths</span></a></li><br><li>Learn about and search Cheshire marriage bonds and allegations. <br><br><span class=\"star notranslate\">☆</span><a href=\"https://www.familysearch.org/wiki/en/England,_Cheshire_Parish_Registers_-_FamilySearch_Historical_Records\" target=\"_blank\"> <img src=\"../img/doc.png\" width=\"20\"> <span class=\"re\">FS: Cheshire Marriage Bonds and Allegations</span></a></li><br><li>See a <a class=\"lk\" href=\"https://www.familysearch.org/wiki/en/Cheshire_Parishes\" target=\"_blank\">list of civil parishes with links</a> on the FamilySearch Wiki.</li><li>Explore Cheshire civil registration on the <span class=\"star notranslate\">☆</span><a class=\"lk\" href=\"http://www.genuki.org.uk/big/eng/CHS/#CivilReg\" target=\"_blank\"><img src=\"../img/d.png\" width=\"2\">Gen UKI site</a>.</li><li>Browse the <a class=\"lk\" href=\"http://www.ukbmd.org.uk/genuki/reg/chs.html\" target=\"_blank\">Cheshire registration districts</a> on the Gen UKI site.</li><li>Explore <a class=\"lk\" href=\"http://www.cheshirebmd.org.uk/births.php\" target=\"_blank\">Cheshire birth records</a> on the Cheshire BMD site.</li><li>Explore <a class=\"lk\" href=\"http://www.cheshirebmd.org.uk/deaths.php\" target=\"_blank\">Cheshire marriage records</a> on the Cheshire BMD site.</li><li>Explore the <span class=\"star notranslate\">☆</span><a class=\"lk\" href=\"http://joinermarriageindex.co.uk/marriage-records/Cheshire/\" target=\"_blank\"><img src=\"../img/d.png\" width=\"2\">Joiner Marriage Index</a> for Cheshire.</li><li>Explore <a class=\"lk\" href=\"http://www.cheshirebmd.org.uk/deaths.php\" target=\"_blank\">Cheshire death records</a> on the Cheshire BMD site.</li><li>Search the <span class=\"star notranslate\">☆</span><a class=\"lk\" href=\"https://www.freebmd.org.uk/search\" target=\"_blank\"><img src=\"../img/d.png\" width=\"2\">FreeBMD UK site</a> for BMD records.</li></ol>",
                    "resources": []
                }
            },
            {
                "name": "Explore Cheshire census and other records.",
                "content": {
                    "hidden": [
                        {
                            "type": "exercises",
                            "content": "<ul style=\"list-style: none; margin-left: -20px;\"><li>* Good: Using the articles and videos in this Choice, write down key learnings for civil registration and other records. Then use the learnings for searches for an ancestor.</li><li>* Proficient: Same as above, for two or more ancestors. </li></ul><hr style=\"margin-left: 20px;\">"
                        }
                    ],
                    "images": [],
                    "text": "<ol><li>Learn about Cheshire Census Surname Indexes in FamilySearch. <br><br><span class=\"star notranslate\">☆</span><a href=\"https://familysearch.org/wiki/en/Cheshire_Census_Surname_Indexes_at_the_Family_History_Library\" target=\"_blank\"> <img src=\"../img/doc.png\" width=\"20\"> <span class=\"re\">FS Wiki: Census Surname Indexes</span></a></li><br><li>Learn about Cheshire census records and electoral registers. <br><br><span class=\"star notranslate\">☆</span><a href=\"https://www.cheshirearchives.org.uk/family-history/census-returns.aspx\" target=\"_blank\"> <img src=\"../img/doc.png\" width=\"20\"> <span class=\"re\">Census and Electoral Registers</span></a></li><br><li>Explore <span class=\"star notranslate\">☆</span><a class=\"lk\" href=\"https://www.freecen.org.uk/\" target=\"_blank\"><img src=\"../img/d.png\" width=\"2\">Cheshire census records </a> on the FreeCen site.</li><li>Browse a <a class=\"lk\" href=\"http://cheshiredirectories.manuscripteye.com/index.htm\" target=\"_blank\">collection of Cheshire directories</a> online.</li><li>Explore <span class=\"star notranslate\">☆</span><a class=\"lk\" href=\"https://www.genuki.org.uk/big/eng/CHS#VotingRegisters\" target=\"_blank\"><img src=\"../img/d.png\" width=\"2\">voting registers</a> on the GenUKI site.</li></ol><p style=\"margin-left:44px\"><img src=\"../img/bolt1.png\" width=\"20px\"> QUIKLinks</p>",
                    "resources": []
                }
            }
        ]
    },
    {
        "nav_name": "Church and Cemetery Records",
        "name": "Church and Cemetery Records",
        "section_name": "Learn about Cheshire church and cemetery records.",
        "summary": "",
        "choices": [
            {
                "name": "Learn about Cheshire church records.",
                "content": {
                    "hidden": [
                        {
                            "type": "exercises",
                            "content": "<ul style=\"list-style: none; margin-left: -20px;\"><li>* Good: Using the articles and videos in this Choice, write down key learnings for church records. Then use the learnings for searches for an ancestor.</li><li>* Proficient: Same as above, for two or more ancestors. </li></ul><hr style=\"margin-left: 20px;\">"
                        }
                    ],
                    "images": [
                        "https://www.thefhguide.com/img/x-en-chs-church.jpg"
                    ],
                    "text": "<ol><a href=\"https://commons.wikimedia.org/wiki/File:St_Alban%27s_Church,_Tattenhall.jpg\" target=\"_blank\"> <img src=\"../img/x-en-chs-church.jpg\" alt=\"\" width=\"450px\" border=\"1\" style=\"float:right; margin-top: 16px; margin-left: 16px; border:1px solid #000; padding:0px;\"></a><li>Get an overview of Cheshire church records in this article. <br><br><span class=\"star notranslate\">☆</span><a href=\"https://familysearch.org/wiki/en/Cheshire_Church_Records\" target=\"_blank\"> <img src=\"../img/doc.png\" width=\"20\"> <span class=\"re\">FS—Cheshire Church Records</span></a></li><br><li>Learn about Cheshire parish registers for baptisms, marriages, and burials. <br><br><span class=\"star notranslate\">☆</span><a href=\"https://www.cheshirearchives.org.uk/family-history/parish-registers-and-bishops.aspx\" target=\"_blank\"> <img src=\"../img/doc.png\" width=\"20\"> <span class=\"re\">Baptisms, Marriages, and Burials (ChehireArchives.org)</span></a></li><br><li>Explore the <span class=\"star notranslate\">☆</span><a class=\"lk\" href=\"http://www.genuki.org.uk/big/eng/CHS/#ChurchRecords\" target=\"_blank\"><img src=\"../img/d.png\" width=\"2\">church records link</a> on the GenUKI Cheshire site.</li><li>Use this <span class=\"star notranslate\">☆</span><a class=\"lk\" href=\"https://familysearch.org/wiki/en/Cheshire_Parishes\" target=\"_blank\"><img src=\"../img/d.png\" width=\"2\">parish page</a> to explore parish records in Cheshire.</li><li>Explore marriage records in the Chester Diocese in <a class=\"lk\" href=\"http://englishmarriages.byu.edu/\" target=\"_blank\">Bertram Merrell's Index of English Marriages</a>, hosted at BYU.</li></ol>",
                    "resources": []
                }
            },
            {
                "name": "Explore Cheshire cemetery records.",
                "content": {
                    "hidden": [
                        {
                            "type": "exercises",
                            "content": "<ul style=\"list-style: none; margin-left: -20px;\"><li>* Good: Using the articles and videos in this Choice, write down key learnings for cemetery records. Then use the learnings for searches for an ancestor.</li><li>* Proficient: Same as above, for two or more ancestors. </li></ul><hr style=\"margin-left: 20px;\">"
                        }
                    ],
                    "images": [],
                    "text": "<ol><li>Explore Cheshire cemetery records on the <span class=\"star notranslate\">☆</span><a class=\"lk\" href=\"http://allenglishrecords.com/cheshire/cemeteries.shtml\" target=\"_blank\"><img src=\"../img/d.png\" width=\"2\">AllEnglishRecords</a>.</li><li>Explore the <a class=\"lk\" href=\"http://places.wishful-thinking.org.uk/CHS/MIs.html\" target=\"_blank\">Cheshire Memorial Inscription Collection</a> online.</li><li>Search the <span class=\"star notranslate\">☆</span><a class=\"lk\" href=\"https://www.findagrave.com/cemetery/search?cemetery-name=&amp;cemetery-loc=Cheshire%2C+England&amp;only-with-cemeteries=cemOnly&amp;locationId=state_4209\" target=\"_blank\"><img src=\"../img/d.png\" width=\"2\">Find a Grave site</a> for cemetery records.</li><li>Search the <span class=\"star notranslate\">☆</span><a class=\"lk\" href=\"http://billiongraves.com/pages/search/\" target=\"_blank\"><img src=\"../img/d.png\" width=\"2\">BillionGraves site</a> for cemetery records.</li></ol><p style=\"margin-left:44px\"><img src=\"../img/bolt1.png\" width=\"20px\"> QUIKLinks</p>",
                    "resources": []
                }
            }
        ]
    },
    {
        "nav_name": "Probate, Land and Court",
        "name": "Probate, Land and Court Records",
        "section_name": "Learn about Cheshire probate and land records.",
        "summary": "",
        "choices": [
            {
                "name": "Learn about Cheshire probate and land records.",
                "content": {
                    "hidden": [
                        {
                            "type": "exercises",
                            "content": "<ul style=\"list-style: none; margin-left: -20px;\"><li>* Good: Using the articles and videos in this Choice, write down key learnings for probate and land records. Then use the learnings for searches for an ancestor.</li><li>* Proficient: Same as above, for two or more ancestors. </li></ul><hr style=\"margin-left: 20px;\">"
                        }
                    ],
                    "images": [
                        "https://www.thefhguide.com/img/x-en-chs-land.jpg"
                    ],
                    "text": "<ol><a href=\"https://en.wikipedia.org/wiki/Cheshire#/media/File:Beeston_walk.JPG\" target=\"_blank\"><img src=\"../img/x-en-chs-land.jpg\" alt=\"\" width=\"100%\" style=\"float:right; margin-left: 16px; margin-top: 8px; margin-bottom: 16px; max-width: 400px; border:1px solid #000; padding:0px;\"></a><li>Learn more about Cheshire probate records in this FamilySearch Wiki article. <br><br><span class=\"star notranslate\">☆</span><a href=\"https://familysearch.org/wiki/en/Cheshire_Probate_Records\" target=\"_blank\"> <img src=\"../img/doc.png\" width=\"20\"> <span class=\"re\">FS—Wiki: Cheshire Probate Records</span></a></li><br><li>Learn about and search Cheshire probate records. <br><br><span class=\"star notranslate\">☆</span><a href=\"https://www.familysearch.org/wiki/en/England,_Cheshire_Probate_Records_-_FamilySearch_Historical_Records\" target=\"_blank\"> <img src=\"../img/doc.png\" width=\"20\"> <span class=\"re\">FS: Cheshire Probate Records</span></a></li><br><li>Learn about and search Cheshire wills and probate records. <br><br><span class=\"star notranslate\">☆</span><a href=\"https://www.cheshirearchives.org.uk/family-history/wills-and-probate-records.aspx\" target=\"_blank\"> <img src=\"../img/doc.png\" width=\"20\"> <span class=\"re\">Wills and Probate Records</span></a></li><br><li>Learn about and search Cheshire land tax assessments. <br><br><span class=\"star notranslate\">☆</span><a href=\"https://www.familysearch.org/wiki/en/England,_Cheshire,_Land_Tax_Assessments_-_FamilySearch_Historical_Records\" target=\"_blank\"> <img src=\"../img/doc.png\" width=\"20\"> <span class=\"re\">FS: Cheshire Land Tax Assessment Records</span></a></li><br><li>Explore deeds by surname on the <a class=\"lk\" href=\"http://www.familydeeds.org/cheshire.php\" target=\"_blank\">FamilyDeeds site</a>.</li></ol><p style=\"margin-left:44px\"><img src=\"../img/bolt1.png\" width=\"20px\"> QUIKLinks</p>",
                    "resources": []
                }
            }
        ]
    },
    {
        "nav_name": "Maps and Gazetteers",
        "name": "Maps and Gazetteers",
        "section_name": "Learn about Cheshire maps and gazetteers.",
        "summary": "",
        "choices": [
            {
                "name": "Explore Cheshire maps and gazetteers.",
                "content": {
                    "hidden": [],
                    "images": [],
                    "text": "<ol><li>Learn about Cheshire maps in this FamilySearch Wiki article. <br><br><span class=\"star notranslate\">☆</span><a href=\"https://familysearch.org/wiki/en/Cheshire_Maps\" target=\"_blank\"> <img src=\"../img/doc.png\" width=\"20\"> <span class=\"re\">FS—Wiki: Cheshire Probate Records</span></a></li><br><li>Explore <span class=\"star notranslate\">☆</span><a class=\"lk\" href=\"https://freepages.rootsweb.com/~genmaps/genealogy/genfiles/COU_Pages/ENG_pages/chs.htm\" target=\"_blank\"><img src=\"../img/d.png\" width=\"2\">historical maps</a> on the GenMaps site.</li><li>Explore the <span class=\"star notranslate\">☆</span><a class=\"lk\" href=\"http://www.davidrumsey.com/luna/servlet/view/search?sort=Pub_List_No_InitialSort%2CPub_Date%2CPub_List_No%2CSeries_No&amp;q=cheshire&amp;search=Go\" target=\"_blank\"><img src=\"../img/d.png\" width=\"2\">David Rumsey collection</a> of Cheshire maps.</li><li>Explore the <span class=\"star notranslate\">☆</span><a class=\"lk\" href=\"http://www.genuki.org.uk/big/eng/CHS/#Maps\" target=\"_blank\"><img src=\"../img/d.png\" width=\"2\">maps link</a> on the GenUKI Cheshire site.</li><li>Explore the online <span class=\"star notranslate\">☆</span><a class=\"lk\" href=\"http://www.genuki.org.uk/big/Gazetteers\" target=\"_blank\"><img src=\"../img/d.png\" width=\"2\">Gazetteer</a> on the GenUKI site.</li><li>Explore a collection of <a class=\"lk\" href=\"https://maps.cheshireeast.gov.uk/tithemaps/\" target=\"_blank\">Cheshire tithe maps</a>.</li><br><br><br></ol>",
                    "resources": []
                }
            }
        ]
    },
    {
        "nav_name": "Newspapers",
        "name": "Newspapers",
        "section_name": "Learn about Cheshire newspapers.",
        "summary": "",
        "choices": [
            {
                "name": "Explore Cheshire newspapers.",
                "content": {
                    "hidden": [],
                    "images": [],
                    "text": "<ol><li>Learn about Cheshire newspapers in this FamilySearch Wiki article. <br><br><span class=\"star notranslate\">☆</span><a href=\"https://familysearch.org/wiki/en/Cheshire_Newspapers\" target=\"_blank\"> <img src=\"../img/doc.png\" width=\"20\"> <span class=\"re\">FS—Wiki: Cheshire Newspapers</span></a></li><br><li>Search Cheshire newspapers in the <span class=\"star notranslate\">☆</span><a class=\"lk\" href=\"http://www.abyznewslinks.com/ukingnw.htm\" target=\"_blank\"><img src=\"../img/d.png\" width=\"2\">ABYZ News Link</a> site.</li></ol>",
                    "resources": []
                }
            }
        ]
    },
    {
        "nav_name": "Websites",
        "name": "Websites",
        "section_name": "Explore additional websites for research.",
        "summary": "",
        "choices": [
            {
                "name": "There are a number of websites with valuable resources for Cheshire research.",
                "content": {
                    "hidden": [],
                    "images": [],
                    "text": "<ol><li>Explore links in <a class=\"lk\" href=\"http://www.cyndislist.com/uk/eng/counties/chs/\" target=\"_blank\">Cyndi's List</a>.</li><li>Explore links in <a class=\"lk\" href=\"http://www.genealogylinks.net/uk/england/cheshire/index.html\" target=\"_blank\">GenealogyLinks.net</a>.</li> </ol>",
                    "resources": []
                }
            }
        ]
    },
    {
        "nav_name": "Search Records",
        "name": "Search Records",
        "section_name": "Search records from Cheshire.",
        "summary": "",
        "choices": [
            {
                "name": "Explore record collections.",
                "content": {
                    "hidden": [],
                    "images": [],
                    "text": "<ol><li>Use the England Record Selection Table to decide on records to search. <br><br><span class=\"star notranslate\">☆</span><a href=\"https://familysearch.org/wiki/en/England_Record_Selection_Table\" target=\"_blank\"> <img src=\"../img/doc.png\" width=\"20\"> <span class=\"re\">FS—England Record Selection Table</span></a></li><br><li>Explore the <a class=\"lk\" href=\"https://familysearch.org/wiki/en/Cheshire,_England_Online_Genealogy_Records\" target=\"_blank\">FamilySearch page</a> for online genealogy records.</li><li>Explore additional record collections in <a class=\"lk\" href=\"https://www.ancestry.com/search/collections/catalog/?keyword=Cheshire,%20England\" target=\"_blank\">Ancestry</a>.</li><li>Explore additional record collections in <a class=\"lk\" href=\"https://search.findmypast.com/historical-records?page=1&amp;region=england&amp;subcountry=cheshire\" target=\"_blank\">Findmypast</a>.</li></ol>",
                    "resources": []
                }
            },
            {
                "name": "Use QUIKLinks to quickly search record the most common record collections for Cheshire.",
                "content": {
                    "hidden": [],
                    "images": [],
                    "text": "",
                    "resources": []
                }
            }
        ]
    },
    {
        "nav_name": "Get Help",
        "name": "Get Help",
        "section_name": "Get help with your Cheshire research.",
        "summary": "",
        "choices": [
            {
                "name": "Use Facebook pages to get answers to your questions.",
                "content": {
                    "hidden": [],
                    "images": [
                        "https://www.thefhguide.com/img/y-facebook.jpg"
                    ],
                    "text": "<ol><a href=\"../img/y-facebook.jpg\" target=\"_blank\"> <img src=\"../img/y-facebook.jpg\" alt=\"\" height=\"170px\" border=\"1\" style=\"float:right; margin-top: 16px; margin-left: 36px\"></a> <li> Visit the <a class=\"lk\" href=\"https://www.facebook.com/groups/269182469822568/\" target=\"_blank\">Cheshire Genealogy page</a> on Facebook.</li> </ol>",
                    "resources": []
                }
            },
            {
                "name": "Join a mailing list or message board for Cheshire research.",
                "content": {
                    "hidden": [],
                    "images": [],
                    "text": "<ol><li>Join the <span class=\"star notranslate\">☆</span><a class=\"lk\" href=\"http://www.rootschat.com/forum/england/\" target=\"_blank\"><img src=\"../img/d.png\" width=\"2\">RootsChat forum</a> and post questions about Cheshire research.</li><li>Search the <span class=\"star notranslate\">☆</span><a class=\"lk\" href=\"http://bigfile.rootsweb.ancestry.com/cgi-bin/listsearch\" target=\"_blank\"><img src=\"../img/d.png\" width=\"2\">RootsWeb site </a> for Cheshire research mailing lists.</li><li>Explore the <span class=\"star notranslate\">☆</span><a class=\"lk\" href=\"http://www.cyndislist.com/uk/eng/counties/chs/social/\" target=\"_blank\"><img src=\"../img/d.png\" width=\"2\"> Cheshire research mailing lists</a> on Cyndi's List.</li></ol>",
                    "resources": []
                }
            },
            {
                "name": "Learn about Cheshire genealogy societies.",
                "content": {
                    "hidden": [],
                    "images": [],
                    "text": "<ol><li>Learn about genealogy societies in Cheshire in this FamilySearch Wiki article. <br><br><span class=\"star notranslate\">☆</span><a class=\"lk\" href=\"https://familysearch.org/wiki/en/Cheshire_Societies\" target=\"_blank\"> <img src=\"../img/doc.png\" width=\"20\"> <span class=\"re\">FS—Wiki: Cheshire Societies</span></a></li><br><li>Explore <span class=\"star notranslate\">☆</span><a class=\"lk\" href=\"http://www.genuki.org.uk/big/eng/CHS#Societies\" target=\"_blank\"><img src=\"../img/d.png\" width=\"2\">genealogy societies</a> on the GenUKI Cheshire site.</li><li>Explore <span class=\"star notranslate\">☆</span><a class=\"lk\" href=\"http://www.cyndislist.com/uk/eng/counties/chs/societies/\" target=\"_blank\"><img src=\"../img/d.png\" width=\"2\">English genealogy society sites</a> on Cyndi's list.</li></ol>",
                    "resources": []
                }
            }
        ]
    }
]